Metadata-Version: 1.0
Name: luckynum
Version: 0.1.1
Summary: to get a luckynum
Home-page: UNKNOWN
Author: MoonKnight
Author-email: 919024219@qq.com
License: MIT Licence
Keywords: pip,MoonKight
Platform: any
